{
  "layers": [
    {
      "name": "color-modes--light",
      "dependencies": [],
      "parameters": {
        "section-name": "light"
      },
      "isStatic": false,
      "variables": [
        {
          "name": "semantic.action.textColor.error",
          "key": "--semantic-action-text-color-error",
          "type": "textColor",
          "description": "",
          "value": "{--brand-color-error-700}"
        },
        {
          "name": "semantic.action.textColor.secondary",
          "key": "--semantic-action-text-color-secondary",
          "type": "textColor",
          "description": "",
          "value": "{--brand-color-primary-500}"
        },
        {
          "name": "semantic.action.textColor.default",
          "key": "--semantic-action-text-color-default",
          "type": "textColor",
          "description": "",
          "value": "{--brand-interactive-neutral-white}"
        },
        {
          "name": "semantic.action.backgroundColor.default",
          "key": "--semantic-action-background-color-default",
          "type": "backgroundColor",
          "description": "",
          "value": "{--brand-color-primary-500}"
        },
        {
          "name": "semantic.action.backgroundColor.secondary",
          "key": "--semantic-action-background-color-secondary",
          "type": "backgroundColor",
          "description": "",
          "value": "{--brand-interactive-neutral-white}"
        },
        {
          "name": "semantic.action.borderColor.default",
          "key": "--semantic-action-border-color-default",
          "type": "borderColor",
          "description": "",
          "value": "{--brand-color-neutral-transparent}"
        },
        {
          "name": "semantic.action.borderColor.error",
          "key": "--semantic-action-border-color-error",
          "type": "borderColor",
          "description": "",
          "value": "{--brand-color-error-700}"
        },
        {
          "name": "semantic.action.borderColor.secondary",
          "key": "--semantic-action-border-color-secondary",
          "type": "borderColor",
          "description": "",
          "value": "{--brand-color-primary-500}"
        },
        {
          "name": "semantic.static.textColor.strong",
          "key": "--semantic-static-text-color-strong",
          "type": "textColor",
          "description": "",
          "value": "{--brand-color-neutral-black}"
        },
        {
          "name": "semantic.static.textColor.default",
          "key": "--semantic-static-text-color-default",
          "type": "textColor",
          "description": "",
          "value": "{--brand-color-neutral-700}"
        },
        {
          "name": "semantic.static.borderColor.default",
          "key": "--semantic-static-border-color-default",
          "type": "borderColor",
          "description": "",
          "value": "{--brand-color-error-700}"
        },
        {
          "name": "semantic.static.borderColor.strong",
          "key": "--semantic-static-border-color-strong",
          "type": "borderColor",
          "description": "",
          "value": "{--brand-color-neutral-300}"
        },
        {
          "name": "semantic.static.backgroundColor.default",
          "key": "--semantic-static-background-color-default",
          "type": "backgroundColor",
          "description": "",
          "value": "{--brand-color-neutral-white}"
        },
        {
          "name": "semantic.static.backgroundColor.muted",
          "key": "--semantic-static-background-color-muted",
          "type": "backgroundColor",
          "description": "",
          "value": "{--brand-color-neutral-100}"
        }
      ]
    },
    {
      "name": "color-modes--dark",
      "dependencies": [],
      "parameters": {
        "section-name": "dark"
      },
      "isStatic": false,
      "variables": [
        {
          "name": "semantic.action.textColor.error",
          "key": "--semantic-action-text-color-error",
          "type": "textColor",
          "description": "",
          "value": "rgba(255, 77, 77, 1.00)"
        },
        {
          "name": "semantic.action.textColor.secondary",
          "key": "--semantic-action-text-color-secondary",
          "type": "textColor",
          "description": "",
          "value": "{--brand-color-neutral-100}"
        },
        {
          "name": "semantic.action.textColor.default",
          "key": "--semantic-action-text-color-default",
          "type": "textColor",
          "description": "",
          "value": "{--brand-color-neutral-white}"
        },
        {
          "name": "semantic.action.backgroundColor.default",
          "key": "--semantic-action-background-color-default",
          "type": "backgroundColor",
          "description": "",
          "value": "{--brand-color-neutral-800}"
        },
        {
          "name": "semantic.action.backgroundColor.secondary",
          "key": "--semantic-action-background-color-secondary",
          "type": "backgroundColor",
          "description": "",
          "value": "{--brand-color-neutral-800}"
        },
        {
          "name": "semantic.action.borderColor.default",
          "key": "--semantic-action-border-color-default",
          "type": "borderColor",
          "description": "",
          "value": "{--brand-color-primary-500}"
        },
        {
          "name": "semantic.action.borderColor.error",
          "key": "--semantic-action-border-color-error",
          "type": "borderColor",
          "description": "",
          "value": "{--brand-color-error-700}"
        },
        {
          "name": "semantic.action.borderColor.secondary",
          "key": "--semantic-action-border-color-secondary",
          "type": "borderColor",
          "description": "",
          "value": "{--brand-color-primary-500}"
        },
        {
          "name": "semantic.static.textColor.strong",
          "key": "--semantic-static-text-color-strong",
          "type": "textColor",
          "description": "",
          "value": "{--brand-color-neutral-white}"
        },
        {
          "name": "semantic.static.textColor.default",
          "key": "--semantic-static-text-color-default",
          "type": "textColor",
          "description": "",
          "value": "{--brand-color-neutral-300}"
        },
        {
          "name": "semantic.static.borderColor.default",
          "key": "--semantic-static-border-color-default",
          "type": "borderColor",
          "description": "",
          "value": "{--brand-interactive-error-700}"
        },
        {
          "name": "semantic.static.borderColor.strong",
          "key": "--semantic-static-border-color-strong",
          "type": "borderColor",
          "description": "",
          "value": "{--brand-color-neutral-700}"
        },
        {
          "name": "semantic.static.backgroundColor.default",
          "key": "--semantic-static-background-color-default",
          "type": "backgroundColor",
          "description": "",
          "value": "{--brand-color-neutral-800}"
        },
        {
          "name": "semantic.static.backgroundColor.muted",
          "key": "--semantic-static-background-color-muted",
          "type": "backgroundColor",
          "description": "",
          "value": "{--brand-color-neutral-900}"
        }
      ]
    },
    {
      "name": "brand--brand-1",
      "dependencies": [],
      "parameters": {
        "section-name": "brand-1"
      },
      "isStatic": false,
      "variables": [
        {
          "name": "brand.color.neutral.white",
          "key": "--brand-color-neutral-white",
          "type": "colors",
          "description": "",
          "value": "rgba(255, 255, 255, 1.00)"
        },
        {
          "name": "brand.interactive.neutral.white",
          "key": "--brand-interactive-neutral-white",
          "type": "colors",
          "description": "",
          "value": "rgba(255, 255, 255, 1.00)"
        },
        {
          "name": "brand.interactive.neutral.100",
          "key": "--brand-interactive-neutral-100",
          "type": "colors",
          "description": "",
          "value": "rgba(241, 241, 241, 1.00)"
        },
        {
          "name": "brand.interactive.neutral.300",
          "key": "--brand-interactive-neutral-300",
          "type": "colors",
          "description": "",
          "value": "rgba(214, 214, 214, 1.00)"
        },
        {
          "name": "brand.interactive.neutral.700",
          "key": "--brand-interactive-neutral-700",
          "type": "colors",
          "description": "",
          "value": "rgba(87, 87, 87, 1.00)"
        },
        {
          "name": "brand.interactive.neutral.800",
          "key": "--brand-interactive-neutral-800",
          "type": "colors",
          "description": "",
          "value": "rgba(40, 40, 40, 1.00)"
        },
        {
          "name": "brand.interactive.neutral.black",
          "key": "--brand-interactive-neutral-black",
          "type": "colors",
          "description": "",
          "value": "rgba(0, 0, 0, 1.00)"
        },
        {
          "name": "brand.interactive.primary.500",
          "key": "--brand-interactive-primary-500",
          "type": "colors",
          "description": "",
          "value": "rgba(26, 34, 242, 1.00)"
        },
        {
          "name": "brand.interactive.error.700",
          "key": "--brand-interactive-error-700",
          "type": "colors",
          "description": "",
          "value": "rgba(216, 16, 16, 1.00)"
        },
        {
          "name": "brand.color.primary.500",
          "key": "--brand-color-primary-500",
          "type": "colors",
          "description": "",
          "value": "rgba(26, 34, 242, 1.00)"
        },
        {
          "name": "brand.color.neutral.100",
          "key": "--brand-color-neutral-100",
          "type": "colors",
          "description": "",
          "value": "rgba(241, 241, 241, 1.00)"
        },
        {
          "name": "brand.color.neutral.300",
          "key": "--brand-color-neutral-300",
          "type": "colors",
          "description": "",
          "value": "rgba(214, 214, 214, 1.00)"
        },
        {
          "name": "brand.color.neutral.700",
          "key": "--brand-color-neutral-700",
          "type": "colors",
          "description": "",
          "value": "rgba(87, 87, 87, 1.00)"
        },
        {
          "name": "brand.color.neutral.800",
          "key": "--brand-color-neutral-800",
          "type": "colors",
          "description": "",
          "value": "rgba(55, 55, 55, 1.00)"
        },
        {
          "name": "brand.color.neutral.900",
          "key": "--brand-color-neutral-900",
          "type": "colors",
          "description": "",
          "value": "rgba(40, 40, 40, 1.00)"
        },
        {
          "name": "brand.color.neutral.black",
          "key": "--brand-color-neutral-black",
          "type": "colors",
          "description": "",
          "value": "rgba(0, 0, 0, 1.00)"
        },
        {
          "name": "brand.spacing.none",
          "key": "--brand-spacing-none",
          "type": "spacing",
          "description": "",
          "value": "0px"
        },
        {
          "name": "brand.spacing.20",
          "key": "--brand-spacing-20",
          "type": "spacing",
          "description": "",
          "value": "2px"
        },
        {
          "name": "brand.size.20",
          "key": "--brand-size-20",
          "type": "spacing",
          "description": "",
          "value": "2px"
        },
        {
          "name": "brand.size.40",
          "key": "--brand-size-40",
          "type": "spacing",
          "description": "",
          "value": "4px"
        },
        {
          "name": "brand.size.60",
          "key": "--brand-size-60",
          "type": "spacing",
          "description": "",
          "value": "6px"
        },
        {
          "name": "brand.size.80",
          "key": "--brand-size-80",
          "type": "spacing",
          "description": "",
          "value": "8px"
        },
        {
          "name": "brand.size.160",
          "key": "--brand-size-160",
          "type": "spacing",
          "description": "",
          "value": "16px"
        },
        {
          "name": "brand.size.200",
          "key": "--brand-size-200",
          "type": "spacing",
          "description": "",
          "value": "20px"
        },
        {
          "name": "brand.size.240",
          "key": "--brand-size-240",
          "type": "spacing",
          "description": "",
          "value": "24px"
        },
        {
          "name": "brand.size.360",
          "key": "--brand-size-360",
          "type": "spacing",
          "description": "",
          "value": "36px"
        },
        {
          "name": "brand.spacing.40",
          "key": "--brand-spacing-40",
          "type": "spacing",
          "description": "",
          "value": "4px"
        },
        {
          "name": "brand.spacing.60",
          "key": "--brand-spacing-60",
          "type": "spacing",
          "description": "",
          "value": "6px"
        },
        {
          "name": "brand.spacing.80",
          "key": "--brand-spacing-80",
          "type": "spacing",
          "description": "",
          "value": "8px"
        },
        {
          "name": "brand.spacing.160",
          "key": "--brand-spacing-160",
          "type": "spacing",
          "description": "",
          "value": "16px"
        },
        {
          "name": "brand.spacing.200",
          "key": "--brand-spacing-200",
          "type": "spacing",
          "description": "",
          "value": "20px"
        },
        {
          "name": "brand.spacing.240",
          "key": "--brand-spacing-240",
          "type": "spacing",
          "description": "",
          "value": "24px"
        },
        {
          "name": "brand.spacing.360",
          "key": "--brand-spacing-360",
          "type": "spacing",
          "description": "",
          "value": "36px"
        },
        {
          "name": "brand.fontFamily.sans",
          "key": "--brand-font-family-sans",
          "type": "fontFamily",
          "description": "",
          "value": "\"Montserrat\""
        },
        {
          "name": "brand.fontSize.xxs",
          "key": "--brand-font-size-xxs",
          "type": "fontSize",
          "description": "",
          "value": "10"
        },
        {
          "name": "brand.fontSize.xs",
          "key": "--brand-font-size-xs",
          "type": "fontSize",
          "description": "",
          "value": "12"
        },
        {
          "name": "brand.fontSize.sm",
          "key": "--brand-font-size-sm",
          "type": "fontSize",
          "description": "",
          "value": "14"
        },
        {
          "name": "brand.fontSize.regular",
          "key": "--brand-font-size-regular",
          "type": "fontSize",
          "description": "",
          "value": "16"
        },
        {
          "name": "brand.fontSize.lg",
          "key": "--brand-font-size-lg",
          "type": "fontSize",
          "description": "",
          "value": "20"
        },
        {
          "name": "brand.fontSize.xl",
          "key": "--brand-font-size-xl",
          "type": "fontSize",
          "description": "",
          "value": "24"
        },
        {
          "name": "brand.fontSize.xxl",
          "key": "--brand-font-size-xxl",
          "type": "fontSize",
          "description": "",
          "value": "36"
        },
        {
          "name": "brand.fontWeight.regular",
          "key": "--brand-font-weight-regular",
          "type": "fontWeight",
          "description": "",
          "value": "400"
        },
        {
          "name": "brand.fontWeight.bold",
          "key": "--brand-font-weight-bold",
          "type": "fontWeight",
          "description": "",
          "value": "700"
        },
        {
          "name": "brand.lineHeight.3",
          "key": "--brand-line-height-3",
          "type": "lineHeight",
          "description": "",
          "value": "12"
        },
        {
          "name": "brand.lineHeight.4",
          "key": "--brand-line-height-4",
          "type": "lineHeight",
          "description": "",
          "value": "16"
        },
        {
          "name": "brand.lineHeight.5",
          "key": "--brand-line-height-5",
          "type": "lineHeight",
          "description": "",
          "value": "20"
        },
        {
          "name": "brand.lineHeight.6",
          "key": "--brand-line-height-6",
          "type": "lineHeight",
          "description": "",
          "value": "24"
        },
        {
          "name": "brand.letterSpacing.tightest",
          "key": "--brand-letter-spacing-tightest",
          "type": "letterSpacing",
          "description": "",
          "value": "-1"
        },
        {
          "name": "brand.lineHeight.100percent",
          "key": "--brand-line-height-100percent",
          "type": "lineHeight",
          "description": "",
          "value": "100"
        },
        {
          "name": "brand.letterSpacing.tighter",
          "key": "--brand-letter-spacing-tighter",
          "type": "letterSpacing",
          "description": "",
          "value": "-0.800000011920929"
        },
        {
          "name": "brand.letterSpacing.tight",
          "key": "--brand-letter-spacing-tight",
          "type": "letterSpacing",
          "description": "",
          "value": "-0.4000000059604645"
        },
        {
          "name": "brand.letterSpacing.regular",
          "key": "--brand-letter-spacing-regular",
          "type": "letterSpacing",
          "description": "",
          "value": "0"
        },
        {
          "name": "brand.letterSpacing.wide",
          "key": "--brand-letter-spacing-wide",
          "type": "letterSpacing",
          "description": "",
          "value": "0.4000000059604645"
        },
        {
          "name": "brand.letterSpacing.wider",
          "key": "--brand-letter-spacing-wider",
          "type": "letterSpacing",
          "description": "",
          "value": "0.800000011920929"
        },
        {
          "name": "brand.letterSpacing.widest",
          "key": "--brand-letter-spacing-widest",
          "type": "letterSpacing",
          "description": "",
          "value": "1"
        },
        {
          "name": "brand.color.error.700",
          "key": "--brand-color-error-700",
          "type": "colors",
          "description": "",
          "value": "rgba(216, 16, 16, 1.00)"
        },
        {
          "name": "brand.borderWidth.05",
          "key": "--brand-border-width-05",
          "type": "borderWidth",
          "description": "",
          "value": "0.5px"
        },
        {
          "name": "brand.borderWidth.10",
          "key": "--brand-border-width-10",
          "type": "borderWidth",
          "description": "",
          "value": "1px"
        },
        {
          "name": "brand.borderWidth.20",
          "key": "--brand-border-width-20",
          "type": "borderWidth",
          "description": "",
          "value": "2px"
        },
        {
          "name": "brand.borderRadius.none",
          "key": "--brand-border-radius-none",
          "type": "borderRadius",
          "description": "",
          "value": "0px"
        },
        {
          "name": "brand.borderRadius.xs",
          "key": "--brand-border-radius-xs",
          "type": "borderRadius",
          "description": "",
          "value": "4px"
        },
        {
          "name": "brand.borderRadius.sm",
          "key": "--brand-border-radius-sm",
          "type": "borderRadius",
          "description": "",
          "value": "8px"
        },
        {
          "name": "brand.borderRadius.md",
          "key": "--brand-border-radius-md",
          "type": "borderRadius",
          "description": "",
          "value": "16px"
        },
        {
          "name": "brand.borderRadius.lg",
          "key": "--brand-border-radius-lg",
          "type": "borderRadius",
          "description": "",
          "value": "32px"
        },
        {
          "name": "brand.color.neutral.transparent",
          "key": "--brand-color-neutral-transparent",
          "type": "colors",
          "description": "",
          "value": "rgba(170, 170, 170, 0.00)"
        }
      ]
    },
    {
      "name": "brand--hot-brand",
      "dependencies": [],
      "parameters": {
        "section-name": "hot-brand"
      },
      "isStatic": false,
      "variables": [
        {
          "name": "brand.color.neutral.white",
          "key": "--brand-color-neutral-white",
          "type": "colors",
          "description": "",
          "value": "rgba(255, 255, 255, 1.00)"
        },
        {
          "name": "brand.interactive.neutral.white",
          "key": "--brand-interactive-neutral-white",
          "type": "colors",
          "description": "",
          "value": "rgba(255, 255, 255, 1.00)"
        },
        {
          "name": "brand.interactive.neutral.100",
          "key": "--brand-interactive-neutral-100",
          "type": "colors",
          "description": "",
          "value": "rgba(241, 241, 241, 1.00)"
        },
        {
          "name": "brand.interactive.neutral.300",
          "key": "--brand-interactive-neutral-300",
          "type": "colors",
          "description": "",
          "value": "rgba(214, 214, 214, 1.00)"
        },
        {
          "name": "brand.interactive.neutral.700",
          "key": "--brand-interactive-neutral-700",
          "type": "colors",
          "description": "",
          "value": "rgba(87, 87, 87, 1.00)"
        },
        {
          "name": "brand.interactive.neutral.800",
          "key": "--brand-interactive-neutral-800",
          "type": "colors",
          "description": "",
          "value": "rgba(40, 40, 40, 1.00)"
        },
        {
          "name": "brand.interactive.neutral.black",
          "key": "--brand-interactive-neutral-black",
          "type": "colors",
          "description": "",
          "value": "rgba(0, 0, 0, 1.00)"
        },
        {
          "name": "brand.interactive.primary.500",
          "key": "--brand-interactive-primary-500",
          "type": "colors",
          "description": "",
          "value": "rgba(186, 158, 0, 1.00)"
        },
        {
          "name": "brand.interactive.error.700",
          "key": "--brand-interactive-error-700",
          "type": "colors",
          "description": "",
          "value": "rgba(216, 93, 16, 1.00)"
        },
        {
          "name": "brand.color.primary.500",
          "key": "--brand-color-primary-500",
          "type": "colors",
          "description": "",
          "value": "rgba(203, 7, 0, 1.00)"
        },
        {
          "name": "brand.color.neutral.100",
          "key": "--brand-color-neutral-100",
          "type": "colors",
          "description": "",
          "value": "rgba(216, 216, 216, 1.00)"
        },
        {
          "name": "brand.color.neutral.300",
          "key": "--brand-color-neutral-300",
          "type": "colors",
          "description": "",
          "value": "rgba(157, 157, 157, 1.00)"
        },
        {
          "name": "brand.color.neutral.700",
          "key": "--brand-color-neutral-700",
          "type": "colors",
          "description": "",
          "value": "rgba(64, 64, 64, 1.00)"
        },
        {
          "name": "brand.color.neutral.800",
          "key": "--brand-color-neutral-800",
          "type": "colors",
          "description": "",
          "value": "rgba(43, 43, 43, 1.00)"
        },
        {
          "name": "brand.color.neutral.900",
          "key": "--brand-color-neutral-900",
          "type": "colors",
          "description": "",
          "value": "rgba(27, 27, 27, 1.00)"
        },
        {
          "name": "brand.color.neutral.black",
          "key": "--brand-color-neutral-black",
          "type": "colors",
          "description": "",
          "value": "rgba(0, 0, 0, 1.00)"
        },
        {
          "name": "brand.spacing.none",
          "key": "--brand-spacing-none",
          "type": "spacing",
          "description": "",
          "value": "0px"
        },
        {
          "name": "brand.spacing.20",
          "key": "--brand-spacing-20",
          "type": "spacing",
          "description": "",
          "value": "3px"
        },
        {
          "name": "brand.size.20",
          "key": "--brand-size-20",
          "type": "spacing",
          "description": "",
          "value": "2px"
        },
        {
          "name": "brand.size.40",
          "key": "--brand-size-40",
          "type": "spacing",
          "description": "",
          "value": "4px"
        },
        {
          "name": "brand.size.60",
          "key": "--brand-size-60",
          "type": "spacing",
          "description": "",
          "value": "6px"
        },
        {
          "name": "brand.size.80",
          "key": "--brand-size-80",
          "type": "spacing",
          "description": "",
          "value": "8px"
        },
        {
          "name": "brand.size.160",
          "key": "--brand-size-160",
          "type": "spacing",
          "description": "",
          "value": "16px"
        },
        {
          "name": "brand.size.200",
          "key": "--brand-size-200",
          "type": "spacing",
          "description": "",
          "value": "20px"
        },
        {
          "name": "brand.size.240",
          "key": "--brand-size-240",
          "type": "spacing",
          "description": "",
          "value": "24px"
        },
        {
          "name": "brand.size.360",
          "key": "--brand-size-360",
          "type": "spacing",
          "description": "",
          "value": "36px"
        },
        {
          "name": "brand.spacing.40",
          "key": "--brand-spacing-40",
          "type": "spacing",
          "description": "",
          "value": "6px"
        },
        {
          "name": "brand.spacing.60",
          "key": "--brand-spacing-60",
          "type": "spacing",
          "description": "",
          "value": "8px"
        },
        {
          "name": "brand.spacing.80",
          "key": "--brand-spacing-80",
          "type": "spacing",
          "description": "",
          "value": "10px"
        },
        {
          "name": "brand.spacing.160",
          "key": "--brand-spacing-160",
          "type": "spacing",
          "description": "",
          "value": "20px"
        },
        {
          "name": "brand.spacing.200",
          "key": "--brand-spacing-200",
          "type": "spacing",
          "description": "",
          "value": "24px"
        },
        {
          "name": "brand.spacing.240",
          "key": "--brand-spacing-240",
          "type": "spacing",
          "description": "",
          "value": "28px"
        },
        {
          "name": "brand.spacing.360",
          "key": "--brand-spacing-360",
          "type": "spacing",
          "description": "",
          "value": "40px"
        },
        {
          "name": "brand.fontFamily.sans",
          "key": "--brand-font-family-sans",
          "type": "fontFamily",
          "description": "",
          "value": "\"Helvetica\""
        },
        {
          "name": "brand.fontSize.xxs",
          "key": "--brand-font-size-xxs",
          "type": "fontSize",
          "description": "",
          "value": "10"
        },
        {
          "name": "brand.fontSize.xs",
          "key": "--brand-font-size-xs",
          "type": "fontSize",
          "description": "",
          "value": "14"
        },
        {
          "name": "brand.fontSize.sm",
          "key": "--brand-font-size-sm",
          "type": "fontSize",
          "description": "",
          "value": "16"
        },
        {
          "name": "brand.fontSize.regular",
          "key": "--brand-font-size-regular",
          "type": "fontSize",
          "description": "",
          "value": "18"
        },
        {
          "name": "brand.fontSize.lg",
          "key": "--brand-font-size-lg",
          "type": "fontSize",
          "description": "",
          "value": "24"
        },
        {
          "name": "brand.fontSize.xl",
          "key": "--brand-font-size-xl",
          "type": "fontSize",
          "description": "",
          "value": "28"
        },
        {
          "name": "brand.fontSize.xxl",
          "key": "--brand-font-size-xxl",
          "type": "fontSize",
          "description": "",
          "value": "40"
        },
        {
          "name": "brand.fontWeight.regular",
          "key": "--brand-font-weight-regular",
          "type": "fontWeight",
          "description": "",
          "value": "300"
        },
        {
          "name": "brand.fontWeight.bold",
          "key": "--brand-font-weight-bold",
          "type": "fontWeight",
          "description": "",
          "value": "900"
        },
        {
          "name": "brand.lineHeight.3",
          "key": "--brand-line-height-3",
          "type": "lineHeight",
          "description": "",
          "value": "14"
        },
        {
          "name": "brand.lineHeight.4",
          "key": "--brand-line-height-4",
          "type": "lineHeight",
          "description": "",
          "value": "18"
        },
        {
          "name": "brand.lineHeight.5",
          "key": "--brand-line-height-5",
          "type": "lineHeight",
          "description": "",
          "value": "22"
        },
        {
          "name": "brand.lineHeight.6",
          "key": "--brand-line-height-6",
          "type": "lineHeight",
          "description": "",
          "value": "28"
        },
        {
          "name": "brand.letterSpacing.tightest",
          "key": "--brand-letter-spacing-tightest",
          "type": "letterSpacing",
          "description": "",
          "value": "-1"
        },
        {
          "name": "brand.lineHeight.100percent",
          "key": "--brand-line-height-100percent",
          "type": "lineHeight",
          "description": "",
          "value": "120"
        },
        {
          "name": "brand.letterSpacing.tighter",
          "key": "--brand-letter-spacing-tighter",
          "type": "letterSpacing",
          "description": "",
          "value": "-0.800000011920929"
        },
        {
          "name": "brand.letterSpacing.tight",
          "key": "--brand-letter-spacing-tight",
          "type": "letterSpacing",
          "description": "",
          "value": "-0.4000000059604645"
        },
        {
          "name": "brand.letterSpacing.regular",
          "key": "--brand-letter-spacing-regular",
          "type": "letterSpacing",
          "description": "",
          "value": "0"
        },
        {
          "name": "brand.letterSpacing.wide",
          "key": "--brand-letter-spacing-wide",
          "type": "letterSpacing",
          "description": "",
          "value": "0.4000000059604645"
        },
        {
          "name": "brand.letterSpacing.wider",
          "key": "--brand-letter-spacing-wider",
          "type": "letterSpacing",
          "description": "",
          "value": "0.800000011920929"
        },
        {
          "name": "brand.letterSpacing.widest",
          "key": "--brand-letter-spacing-widest",
          "type": "letterSpacing",
          "description": "",
          "value": "1"
        },
        {
          "name": "brand.color.error.700",
          "key": "--brand-color-error-700",
          "type": "colors",
          "description": "",
          "value": "rgba(139, 0, 0, 1.00)"
        },
        {
          "name": "brand.borderWidth.05",
          "key": "--brand-border-width-05",
          "type": "borderWidth",
          "description": "",
          "value": "0.5px"
        },
        {
          "name": "brand.borderWidth.10",
          "key": "--brand-border-width-10",
          "type": "borderWidth",
          "description": "",
          "value": "1px"
        },
        {
          "name": "brand.borderWidth.20",
          "key": "--brand-border-width-20",
          "type": "borderWidth",
          "description": "",
          "value": "2px"
        },
        {
          "name": "brand.borderRadius.none",
          "key": "--brand-border-radius-none",
          "type": "borderRadius",
          "description": "",
          "value": "0px"
        },
        {
          "name": "brand.borderRadius.xs",
          "key": "--brand-border-radius-xs",
          "type": "borderRadius",
          "description": "",
          "value": "2px"
        },
        {
          "name": "brand.borderRadius.sm",
          "key": "--brand-border-radius-sm",
          "type": "borderRadius",
          "description": "",
          "value": "4px"
        },
        {
          "name": "brand.borderRadius.md",
          "key": "--brand-border-radius-md",
          "type": "borderRadius",
          "description": "",
          "value": "8px"
        },
        {
          "name": "brand.borderRadius.lg",
          "key": "--brand-border-radius-lg",
          "type": "borderRadius",
          "description": "",
          "value": "16px"
        },
        {
          "name": "brand.color.neutral.transparent",
          "key": "--brand-color-neutral-transparent",
          "type": "colors",
          "description": "",
          "value": "rgba(170, 170, 170, 0.00)"
        }
      ]
    },
    {
      "name": "density--default",
      "dependencies": [],
      "parameters": {
        "section-name": "default"
      },
      "isStatic": false,
      "variables": [
        {
          "name": "density.action.gap.xs",
          "key": "--density-action-gap-xs",
          "type": "gap",
          "description": "",
          "value": "{--brand-spacing-20}"
        },
        {
          "name": "density.action.gap.sm",
          "key": "--density-action-gap-sm",
          "type": "gap",
          "description": "",
          "value": "{--brand-spacing-40}"
        },
        {
          "name": "density.action.gap.md",
          "key": "--density-action-gap-md",
          "type": "gap",
          "description": "",
          "value": "{--brand-spacing-80}"
        },
        {
          "name": "density.action.gap.lg",
          "key": "--density-action-gap-lg",
          "type": "gap",
          "description": "",
          "value": "{--brand-spacing-160}"
        },
        {
          "name": "density.action.gap.xl",
          "key": "--density-action-gap-xl",
          "type": "gap",
          "description": "",
          "value": "{--brand-spacing-240}"
        },
        {
          "name": "density.icon.size.none",
          "key": "--density-icon-size-none",
          "type": "spacing",
          "description": "",
          "value": "{--brand-spacing-none}"
        },
        {
          "name": "density.padding.xs",
          "key": "--density-padding-xs",
          "type": "padding",
          "description": "",
          "value": "{--brand-spacing-20}"
        },
        {
          "name": "density.padding.sm",
          "key": "--density-padding-sm",
          "type": "padding",
          "description": "",
          "value": "{--brand-spacing-40}"
        },
        {
          "name": "density.padding.md",
          "key": "--density-padding-md",
          "type": "padding",
          "description": "",
          "value": "{--brand-spacing-80}"
        },
        {
          "name": "density.padding.lg",
          "key": "--density-padding-lg",
          "type": "padding",
          "description": "",
          "value": "{--brand-spacing-160}"
        },
        {
          "name": "density.padding.xl",
          "key": "--density-padding-xl",
          "type": "padding",
          "description": "",
          "value": "{--brand-spacing-240}"
        },
        {
          "name": "density.icon.size.sm",
          "key": "--density-icon-size-sm",
          "type": "spacing",
          "description": "",
          "value": "{--brand-spacing-40}"
        },
        {
          "name": "density.icon.size.md",
          "key": "--density-icon-size-md",
          "type": "spacing",
          "description": "",
          "value": "{--brand-spacing-80}"
        },
        {
          "name": "density.icon.size.lg",
          "key": "--density-icon-size-lg",
          "type": "spacing",
          "description": "",
          "value": "{--brand-spacing-160}"
        },
        {
          "name": "density.icon.size.xl",
          "key": "--density-icon-size-xl",
          "type": "spacing",
          "description": "",
          "value": "{--brand-spacing-240}"
        },
        {
          "name": "density.action.borderRadius.none",
          "key": "--density-action-border-radius-none",
          "type": "borderRadius",
          "description": "",
          "value": "{--brand-border-radius-none}"
        },
        {
          "name": "density.action.borderRadius.sm",
          "key": "--density-action-border-radius-sm",
          "type": "borderRadius",
          "description": "",
          "value": "{--brand-border-radius-sm}"
        },
        {
          "name": "density.action.borderRadius.default",
          "key": "--density-action-border-radius-default",
          "type": "borderRadius",
          "description": "",
          "value": "{--brand-border-radius-md}"
        },
        {
          "name": "density.static.borderRadius.none",
          "key": "--density-static-border-radius-none",
          "type": "borderRadius",
          "description": "",
          "value": "{--brand-border-radius-none}"
        },
        {
          "name": "density.static.borderRadius.sm",
          "key": "--density-static-border-radius-sm",
          "type": "borderRadius",
          "description": "",
          "value": "{--brand-border-radius-sm}"
        },
        {
          "name": "density.static.borderRadius.md",
          "key": "--density-static-border-radius-md",
          "type": "borderRadius",
          "description": "",
          "value": "{--brand-border-radius-md}"
        },
        {
          "name": "density.static.borderRadius.lg",
          "key": "--density-static-border-radius-lg",
          "type": "borderRadius",
          "description": "",
          "value": "{--brand-border-radius-lg}"
        },
        {
          "name": "density.action.borderWidth.thin",
          "key": "--density-action-border-width-thin",
          "type": "borderWidth",
          "description": "",
          "value": "{--brand-border-width-05}"
        },
        {
          "name": "density.action.borderWidth.default",
          "key": "--density-action-border-width-default",
          "type": "borderWidth",
          "description": "",
          "value": "{--brand-border-width-10}"
        },
        {
          "name": "density.action.borderWidth.thick",
          "key": "--density-action-border-width-thick",
          "type": "borderWidth",
          "description": "",
          "value": "{--brand-border-width-20}"
        }
      ]
    },
    {
      "name": "density--compact",
      "dependencies": [],
      "parameters": {
        "section-name": "compact"
      },
      "isStatic": false,
      "variables": [
        {
          "name": "density.action.gap.xs",
          "key": "--density-action-gap-xs",
          "type": "gap",
          "description": "",
          "value": "0"
        },
        {
          "name": "density.action.gap.sm",
          "key": "--density-action-gap-sm",
          "type": "gap",
          "description": "",
          "value": "0"
        },
        {
          "name": "density.action.gap.md",
          "key": "--density-action-gap-md",
          "type": "gap",
          "description": "",
          "value": "0"
        },
        {
          "name": "density.action.gap.lg",
          "key": "--density-action-gap-lg",
          "type": "gap",
          "description": "",
          "value": "0"
        },
        {
          "name": "density.action.gap.xl",
          "key": "--density-action-gap-xl",
          "type": "gap",
          "description": "",
          "value": "0"
        },
        {
          "name": "density.icon.size.none",
          "key": "--density-icon-size-none",
          "type": "spacing",
          "description": "",
          "value": "0px"
        },
        {
          "name": "density.padding.xs",
          "key": "--density-padding-xs",
          "type": "padding",
          "description": "",
          "value": "0px"
        },
        {
          "name": "density.padding.sm",
          "key": "--density-padding-sm",
          "type": "padding",
          "description": "",
          "value": "0px"
        },
        {
          "name": "density.padding.md",
          "key": "--density-padding-md",
          "type": "padding",
          "description": "",
          "value": "0px"
        },
        {
          "name": "density.padding.lg",
          "key": "--density-padding-lg",
          "type": "padding",
          "description": "",
          "value": "0px"
        },
        {
          "name": "density.padding.xl",
          "key": "--density-padding-xl",
          "type": "padding",
          "description": "",
          "value": "0px"
        },
        {
          "name": "density.icon.size.sm",
          "key": "--density-icon-size-sm",
          "type": "spacing",
          "description": "",
          "value": "0px"
        },
        {
          "name": "density.icon.size.md",
          "key": "--density-icon-size-md",
          "type": "spacing",
          "description": "",
          "value": "0px"
        },
        {
          "name": "density.icon.size.lg",
          "key": "--density-icon-size-lg",
          "type": "spacing",
          "description": "",
          "value": "0px"
        },
        {
          "name": "density.icon.size.xl",
          "key": "--density-icon-size-xl",
          "type": "spacing",
          "description": "",
          "value": "0px"
        },
        {
          "name": "density.action.borderRadius.none",
          "key": "--density-action-border-radius-none",
          "type": "borderRadius",
          "description": "",
          "value": "0px"
        },
        {
          "name": "density.action.borderRadius.sm",
          "key": "--density-action-border-radius-sm",
          "type": "borderRadius",
          "description": "",
          "value": "0px"
        },
        {
          "name": "density.action.borderRadius.default",
          "key": "--density-action-border-radius-default",
          "type": "borderRadius",
          "description": "",
          "value": "0px"
        },
        {
          "name": "density.static.borderRadius.none",
          "key": "--density-static-border-radius-none",
          "type": "borderRadius",
          "description": "",
          "value": "0px"
        },
        {
          "name": "density.static.borderRadius.sm",
          "key": "--density-static-border-radius-sm",
          "type": "borderRadius",
          "description": "",
          "value": "0px"
        },
        {
          "name": "density.static.borderRadius.md",
          "key": "--density-static-border-radius-md",
          "type": "borderRadius",
          "description": "",
          "value": "0px"
        },
        {
          "name": "density.static.borderRadius.lg",
          "key": "--density-static-border-radius-lg",
          "type": "borderRadius",
          "description": "",
          "value": "0px"
        },
        {
          "name": "density.action.borderWidth.thin",
          "key": "--density-action-border-width-thin",
          "type": "borderWidth",
          "description": "",
          "value": "0px"
        },
        {
          "name": "density.action.borderWidth.default",
          "key": "--density-action-border-width-default",
          "type": "borderWidth",
          "description": "",
          "value": "0px"
        },
        {
          "name": "density.action.borderWidth.thick",
          "key": "--density-action-border-width-thick",
          "type": "borderWidth",
          "description": "",
          "value": "0px"
        }
      ]
    },
    {
      "name": "breakpoints--mobile",
      "dependencies": [],
      "parameters": {
        "section-name": "mobile"
      },
      "isStatic": false,
      "variables": [
        {
          "name": "typography.label.fontSize.default",
          "key": "--typography-label-font-size-default",
          "type": "fontSize",
          "description": "",
          "value": "{--brand-font-size-sm}"
        },
        {
          "name": "typography.label.fontWeight.default",
          "key": "--typography-label-font-weight-default",
          "type": "fontWeight",
          "description": "",
          "value": "{--brand-font-weight-bold}"
        },
        {
          "name": "typography.label.lineHeight.default",
          "key": "--typography-label-line-height-default",
          "type": "lineHeight",
          "description": "",
          "value": "{--brand-line-height-4}"
        },
        {
          "name": "typography.label.letterSpacing.default",
          "key": "--typography-label-letter-spacing-default",
          "type": "letterSpacing",
          "description": "",
          "value": "{--brand-letter-spacing-regular}"
        },
        {
          "name": "typography.info.fontSize.default",
          "key": "--typography-info-font-size-default",
          "type": "fontSize",
          "description": "",
          "value": "{--brand-font-size-regular}"
        },
        {
          "name": "typography.info.fontWeight.default",
          "key": "--typography-info-font-weight-default",
          "type": "fontWeight",
          "description": "",
          "value": "{--brand-font-weight-bold}"
        },
        {
          "name": "typography.info.lineHeight.default",
          "key": "--typography-info-line-height-default",
          "type": "lineHeight",
          "description": "",
          "value": "{--brand-line-height-4}"
        },
        {
          "name": "typography.info.letterSpacing.default",
          "key": "--typography-info-letter-spacing-default",
          "type": "letterSpacing",
          "description": "",
          "value": "{--brand-letter-spacing-regular}"
        },
        {
          "name": "breakpoint.action.padding.none",
          "key": "--breakpoint-action-padding-none",
          "type": "padding",
          "description": "",
          "value": "{--brand-spacing-none}"
        },
        {
          "name": "breakpoint.action.padding.xxs",
          "key": "--breakpoint-action-padding-xxs",
          "type": "padding",
          "description": "",
          "value": "{--density-padding-xs}"
        },
        {
          "name": "breakpoint.action.padding.xs",
          "key": "--breakpoint-action-padding-xs",
          "type": "padding",
          "description": "",
          "value": "{--density-padding-sm}"
        },
        {
          "name": "breakpoint.action.padding.sm",
          "key": "--breakpoint-action-padding-sm",
          "type": "padding",
          "description": "",
          "value": "{--density-padding-md}"
        },
        {
          "name": "breakpoint.action.padding.default",
          "key": "--breakpoint-action-padding-default",
          "type": "padding",
          "description": "",
          "value": "{--density-padding-lg}"
        },
        {
          "name": "breakpoint.static.padding.default",
          "key": "--breakpoint-static-padding-default",
          "type": "padding",
          "description": "",
          "value": "{--density-padding-md}"
        },
        {
          "name": "breakpoint.static.padding.sm",
          "key": "--breakpoint-static-padding-sm",
          "type": "padding",
          "description": "",
          "value": "{--density-padding-sm}"
        },
        {
          "name": "breakpoint.action.gap.none",
          "key": "--breakpoint-action-gap-none",
          "type": "gap",
          "description": "",
          "value": "{--brand-spacing-none}"
        },
        {
          "name": "breakpoint.action.gap.xxs",
          "key": "--breakpoint-action-gap-xxs",
          "type": "gap",
          "description": "",
          "value": "{--brand-spacing-20}"
        },
        {
          "name": "breakpoint.action.gap.xs",
          "key": "--breakpoint-action-gap-xs",
          "type": "gap",
          "description": "",
          "value": "{--brand-spacing-40}"
        },
        {
          "name": "breakpoint.action.gap.sm",
          "key": "--breakpoint-action-gap-sm",
          "type": "gap",
          "description": "",
          "value": "{--brand-spacing-60}"
        },
        {
          "name": "breakpoint.static.padding.md",
          "key": "--breakpoint-static-padding-md",
          "type": "padding",
          "description": "",
          "value": "{--density-padding-md}"
        },
        {
          "name": "breakpoint.action.gap.default",
          "key": "--breakpoint-action-gap-default",
          "type": "gap",
          "description": "",
          "value": "{--brand-spacing-80}"
        },
        {
          "name": "breakpoint.action.borderRadius.sm",
          "key": "--breakpoint-action-border-radius-sm",
          "type": "borderRadius",
          "description": "",
          "value": "{--density-action-border-radius-sm}"
        },
        {
          "name": "breakpoint.static.borderRadius.sm",
          "key": "--breakpoint-static-border-radius-sm",
          "type": "borderRadius",
          "description": "",
          "value": "{--density-static-border-radius-sm}"
        },
        {
          "name": "breakpoint.static.borderRadius.md",
          "key": "--breakpoint-static-border-radius-md",
          "type": "borderRadius",
          "description": "",
          "value": "{--density-static-border-radius-md}"
        },
        {
          "name": "typography.body.fontSize.1",
          "key": "--typography-body-font-size-1",
          "type": "fontSize",
          "description": "",
          "value": "{--brand-font-size-regular}"
        },
        {
          "name": "typography.body.fontSize.2",
          "key": "--typography-body-font-size-2",
          "type": "fontSize",
          "description": "",
          "value": "{--brand-font-size-sm}"
        },
        {
          "name": "typography.body.fontWeight.1",
          "key": "--typography-body-font-weight-1",
          "type": "fontWeight",
          "description": "",
          "value": "{--brand-font-weight-bold}"
        },
        {
          "name": "typography.body.fontWeight.2",
          "key": "--typography-body-font-weight-2",
          "type": "fontWeight",
          "description": "",
          "value": "{--brand-font-weight-regular}"
        },
        {
          "name": "typography.body.lineHeight.1",
          "key": "--typography-body-line-height-1",
          "type": "lineHeight",
          "description": "",
          "value": "{--brand-line-height-4}"
        },
        {
          "name": "typography.body.lineHeight.2",
          "key": "--typography-body-line-height-2",
          "type": "lineHeight",
          "description": "",
          "value": "{--brand-line-height-4}"
        },
        {
          "name": "typography.body.letterSpacing.default",
          "key": "--typography-body-letter-spacing-default",
          "type": "letterSpacing",
          "description": "",
          "value": "{--brand-letter-spacing-regular}"
        },
        {
          "name": "typography.title.fontSize.lg",
          "key": "--typography-title-font-size-lg",
          "type": "fontSize",
          "description": "",
          "value": "{--brand-font-size-lg}"
        },
        {
          "name": "typography.title.fontSize.md",
          "key": "--typography-title-font-size-md",
          "type": "fontSize",
          "description": "",
          "value": "{--brand-font-size-regular}"
        },
        {
          "name": "typography.title.fontWeight.default",
          "key": "--typography-title-font-weight-default",
          "type": "fontWeight",
          "description": "",
          "value": "{--brand-font-weight-bold}"
        },
        {
          "name": "typography.title.lineHeight.lg",
          "key": "--typography-title-line-height-lg",
          "type": "lineHeight",
          "description": "",
          "value": "{--brand-line-height-5}"
        },
        {
          "name": "typography.title.lineHeight.md",
          "key": "--typography-title-line-height-md",
          "type": "lineHeight",
          "description": "",
          "value": "{--brand-line-height-4}"
        },
        {
          "name": "typography.title.letterSpacing.default",
          "key": "--typography-title-letter-spacing-default",
          "type": "letterSpacing",
          "description": "",
          "value": "{--brand-letter-spacing-regular}"
        },
        {
          "name": "typography.subtitle.fontSize.lg",
          "key": "--typography-subtitle-font-size-lg",
          "type": "fontSize",
          "description": "",
          "value": "{--brand-font-size-sm}"
        },
        {
          "name": "typography.subtitle.fontSize.md",
          "key": "--typography-subtitle-font-size-md",
          "type": "fontSize",
          "description": "",
          "value": "{--brand-font-size-regular}"
        },
        {
          "name": "typography.subtitle.fontWeight.default",
          "key": "--typography-subtitle-font-weight-default",
          "type": "fontWeight",
          "description": "",
          "value": "{--brand-font-weight-bold}"
        },
        {
          "name": "typography.subtitle.lineHeight.lg",
          "key": "--typography-subtitle-line-height-lg",
          "type": "lineHeight",
          "description": "",
          "value": "{--brand-line-height-5}"
        },
        {
          "name": "typography.subtitle.lineHeight.md",
          "key": "--typography-subtitle-line-height-md",
          "type": "lineHeight",
          "description": "",
          "value": "{--brand-line-height-4}"
        },
        {
          "name": "typography.subtitle.letterSpacing.default",
          "key": "--typography-subtitle-letter-spacing-default",
          "type": "letterSpacing",
          "description": "",
          "value": "{--brand-letter-spacing-regular}"
        }
      ]
    },
    {
      "name": "breakpoints--desktop",
      "dependencies": [],
      "parameters": {
        "section-name": "desktop"
      },
      "isStatic": false,
      "variables": [
        {
          "name": "typography.label.fontSize.default",
          "key": "--typography-label-font-size-default",
          "type": "fontSize",
          "description": "",
          "value": "{--brand-font-size-regular}"
        },
        {
          "name": "typography.label.fontWeight.default",
          "key": "--typography-label-font-weight-default",
          "type": "fontWeight",
          "description": "",
          "value": "{--brand-font-weight-bold}"
        },
        {
          "name": "typography.label.lineHeight.default",
          "key": "--typography-label-line-height-default",
          "type": "lineHeight",
          "description": "",
          "value": "{--brand-line-height-4}"
        },
        {
          "name": "typography.label.letterSpacing.default",
          "key": "--typography-label-letter-spacing-default",
          "type": "letterSpacing",
          "description": "",
          "value": "{--brand-letter-spacing-regular}"
        },
        {
          "name": "typography.info.fontSize.default",
          "key": "--typography-info-font-size-default",
          "type": "fontSize",
          "description": "",
          "value": "{--brand-font-size-lg}"
        },
        {
          "name": "typography.info.fontWeight.default",
          "key": "--typography-info-font-weight-default",
          "type": "fontWeight",
          "description": "",
          "value": "{--brand-font-weight-bold}"
        },
        {
          "name": "typography.info.lineHeight.default",
          "key": "--typography-info-line-height-default",
          "type": "lineHeight",
          "description": "",
          "value": "{--brand-line-height-4}"
        },
        {
          "name": "typography.info.letterSpacing.default",
          "key": "--typography-info-letter-spacing-default",
          "type": "letterSpacing",
          "description": "",
          "value": "{--brand-letter-spacing-regular}"
        },
        {
          "name": "breakpoint.action.padding.none",
          "key": "--breakpoint-action-padding-none",
          "type": "padding",
          "description": "",
          "value": "{--brand-spacing-none}"
        },
        {
          "name": "breakpoint.action.padding.xxs",
          "key": "--breakpoint-action-padding-xxs",
          "type": "padding",
          "description": "",
          "value": "{--density-padding-sm}"
        },
        {
          "name": "breakpoint.action.padding.xs",
          "key": "--breakpoint-action-padding-xs",
          "type": "padding",
          "description": "",
          "value": "{--density-padding-md}"
        },
        {
          "name": "breakpoint.action.padding.sm",
          "key": "--breakpoint-action-padding-sm",
          "type": "padding",
          "description": "",
          "value": "{--density-padding-lg}"
        },
        {
          "name": "breakpoint.action.padding.default",
          "key": "--breakpoint-action-padding-default",
          "type": "padding",
          "description": "",
          "value": "{--density-padding-xl}"
        },
        {
          "name": "breakpoint.static.padding.default",
          "key": "--breakpoint-static-padding-default",
          "type": "padding",
          "description": "",
          "value": "{--density-padding-xl}"
        },
        {
          "name": "breakpoint.static.padding.sm",
          "key": "--breakpoint-static-padding-sm",
          "type": "padding",
          "description": "",
          "value": "{--density-padding-md}"
        },
        {
          "name": "breakpoint.action.gap.none",
          "key": "--breakpoint-action-gap-none",
          "type": "gap",
          "description": "",
          "value": "{--brand-spacing-none}"
        },
        {
          "name": "breakpoint.action.gap.xxs",
          "key": "--breakpoint-action-gap-xxs",
          "type": "gap",
          "description": "",
          "value": "{--brand-spacing-20}"
        },
        {
          "name": "breakpoint.action.gap.xs",
          "key": "--breakpoint-action-gap-xs",
          "type": "gap",
          "description": "",
          "value": "{--brand-spacing-60}"
        },
        {
          "name": "breakpoint.action.gap.sm",
          "key": "--breakpoint-action-gap-sm",
          "type": "gap",
          "description": "",
          "value": "{--brand-spacing-80}"
        },
        {
          "name": "breakpoint.static.padding.md",
          "key": "--breakpoint-static-padding-md",
          "type": "padding",
          "description": "",
          "value": "{--density-padding-lg}"
        },
        {
          "name": "breakpoint.action.gap.default",
          "key": "--breakpoint-action-gap-default",
          "type": "gap",
          "description": "",
          "value": "{--brand-spacing-160}"
        },
        {
          "name": "breakpoint.action.borderRadius.sm",
          "key": "--breakpoint-action-border-radius-sm",
          "type": "borderRadius",
          "description": "",
          "value": "{--density-action-border-radius-default}"
        },
        {
          "name": "breakpoint.static.borderRadius.sm",
          "key": "--breakpoint-static-border-radius-sm",
          "type": "borderRadius",
          "description": "",
          "value": "{--brand-border-radius-md}"
        },
        {
          "name": "breakpoint.static.borderRadius.md",
          "key": "--breakpoint-static-border-radius-md",
          "type": "borderRadius",
          "description": "",
          "value": "{--density-static-border-radius-lg}"
        },
        {
          "name": "typography.body.fontSize.1",
          "key": "--typography-body-font-size-1",
          "type": "fontSize",
          "description": "",
          "value": "{--brand-font-size-lg}"
        },
        {
          "name": "typography.body.fontSize.2",
          "key": "--typography-body-font-size-2",
          "type": "fontSize",
          "description": "",
          "value": "{--brand-font-size-regular}"
        },
        {
          "name": "typography.body.fontWeight.1",
          "key": "--typography-body-font-weight-1",
          "type": "fontWeight",
          "description": "",
          "value": "{--brand-font-weight-bold}"
        },
        {
          "name": "typography.body.fontWeight.2",
          "key": "--typography-body-font-weight-2",
          "type": "fontWeight",
          "description": "",
          "value": "{--brand-font-weight-regular}"
        },
        {
          "name": "typography.body.lineHeight.1",
          "key": "--typography-body-line-height-1",
          "type": "lineHeight",
          "description": "",
          "value": "{--brand-line-height-4}"
        },
        {
          "name": "typography.body.lineHeight.2",
          "key": "--typography-body-line-height-2",
          "type": "lineHeight",
          "description": "",
          "value": "{--brand-line-height-4}"
        },
        {
          "name": "typography.body.letterSpacing.default",
          "key": "--typography-body-letter-spacing-default",
          "type": "letterSpacing",
          "description": "",
          "value": "{--brand-letter-spacing-regular}"
        },
        {
          "name": "typography.title.fontSize.lg",
          "key": "--typography-title-font-size-lg",
          "type": "fontSize",
          "description": "",
          "value": "{--brand-font-size-xl}"
        },
        {
          "name": "typography.title.fontSize.md",
          "key": "--typography-title-font-size-md",
          "type": "fontSize",
          "description": "",
          "value": "{--brand-font-size-lg}"
        },
        {
          "name": "typography.title.fontWeight.default",
          "key": "--typography-title-font-weight-default",
          "type": "fontWeight",
          "description": "",
          "value": "{--brand-font-weight-bold}"
        },
        {
          "name": "typography.title.lineHeight.lg",
          "key": "--typography-title-line-height-lg",
          "type": "lineHeight",
          "description": "",
          "value": "{--brand-line-height-6}"
        },
        {
          "name": "typography.title.lineHeight.md",
          "key": "--typography-title-line-height-md",
          "type": "lineHeight",
          "description": "",
          "value": "{--brand-line-height-5}"
        },
        {
          "name": "typography.title.letterSpacing.default",
          "key": "--typography-title-letter-spacing-default",
          "type": "letterSpacing",
          "description": "",
          "value": "{--brand-letter-spacing-regular}"
        },
        {
          "name": "typography.subtitle.fontSize.lg",
          "key": "--typography-subtitle-font-size-lg",
          "type": "fontSize",
          "description": "",
          "value": "{--brand-font-size-regular}"
        },
        {
          "name": "typography.subtitle.fontSize.md",
          "key": "--typography-subtitle-font-size-md",
          "type": "fontSize",
          "description": "",
          "value": "{--brand-font-size-lg}"
        },
        {
          "name": "typography.subtitle.fontWeight.default",
          "key": "--typography-subtitle-font-weight-default",
          "type": "fontWeight",
          "description": "",
          "value": "{--brand-font-weight-bold}"
        },
        {
          "name": "typography.subtitle.lineHeight.lg",
          "key": "--typography-subtitle-line-height-lg",
          "type": "lineHeight",
          "description": "",
          "value": "{--brand-line-height-6}"
        },
        {
          "name": "typography.subtitle.lineHeight.md",
          "key": "--typography-subtitle-line-height-md",
          "type": "lineHeight",
          "description": "",
          "value": "{--brand-line-height-5}"
        },
        {
          "name": "typography.subtitle.letterSpacing.default",
          "key": "--typography-subtitle-letter-spacing-default",
          "type": "letterSpacing",
          "description": "",
          "value": "{--brand-letter-spacing-regular}"
        }
      ]
    }
  ],
  "order": [
    "color-modes--light",
    "color-modes--dark",
    "brand--brand-1",
    "brand--hot-brand",
    "density--default",
    "density--compact",
    "breakpoints--mobile",
    "breakpoints--desktop"
  ]
}